poetrytest/__init__.py
poetrytest/base.py
poetrytest-0.1.0.dist-info/WHEEL
poetrytest-0.1.0.dist-info/METADATA
poetrytest-0.1.0.dist-info/RECORD
