Metadata-Version: 2.1
Name: poetrytest
Version: 0.1.0
Summary: poetry 测试用
Home-page: https://github.com/mongnet/poetryTest
License: MIT
Author: MonNet
Author-email: 250021520@qq.com
Requires-Python: >=3.6,<4.0
Classifier: License :: OSI Approved :: MIT License
Classifier: Programming Language :: Python :: 3
Classifier: Programming Language :: Python :: 3.6
Classifier: Programming Language :: Python :: 3.7
Classifier: Programming Language :: Python :: 3.8
Requires-Dist: pytest (>=5.4.2,<6.0.0)
Requires-Dist: requests (>=2.23.0,<3.0.0)
Requires-Dist: selenium (>=3.141.0,<4.0.0)
Project-URL: Repository, https://github.com/mongnet/poetryTest
